sislv4utils/__init__.py
sislv4utils/config.py
sislv4utils/elastic.py
sislv4utils/message.py
sislv4utils/mqtt.py
sislv4utils/objectstore.py
sislv4utils/service.py
sislv4utils-0.0.6.dist-info/METADATA
sislv4utils-0.0.6.dist-info/WHEEL
sislv4utils-0.0.6.dist-info/licenses/LICENSE
sislv4utils-0.0.6.dist-info/RECORD
